{
  "lastUpdated": "2025-10-11T05:52:20.594590Z",
  "bundles": [
    {
      "id": 2034,
      "name": "BTC/ADA Bundle",
      "profit": "+12.6%",
      "duration": "22h",
      "risk": "High",
      "assets": [
        {
          "name": "BTC",
          "percentage": 31,
          "color": "#f7931a"
        },
        {
          "name": "ADA",
          "percentage": 24,
          "color": "#0033ad"
        },
        {
          "name": "BNB",
          "percentage": 45,
          "color": "#f3ba2f"
        }
      ],
      "currentInvested": 0.7,
      "timeRemaining": 114,
      "generatedAt": "2025-10-11T05:52:20.594490Z"
    },
    {
      "id": 9601,
      "name": "BNB/BTC Bundle",
      "profit": "+15.7%",
      "duration": "14h",
      "risk": "Medium",
      "assets": [
        {
          "name": "BNB",
          "percentage": 42,
          "color": "#f3ba2f"
        },
        {
          "name": "BTC",
          "percentage": 22,
          "color": "#f7931a"
        },
        {
          "name": "ETH",
          "percentage": 36,
          "color": "#627eea"
        }
      ],
      "currentInvested": 5.68,
      "timeRemaining": 752,
      "generatedAt": "2025-10-11T05:52:20.594519Z"
    },
    {
      "id": 8746,
      "name": "BNB/ADA Bundle",
      "profit": "+13.7%",
      "duration": "7h",
      "risk": "Medium",
      "assets": [
        {
          "name": "BNB",
          "percentage": 21,
          "color": "#f3ba2f"
        },
        {
          "name": "ADA",
          "percentage": 58,
          "color": "#0033ad"
        },
        {
          "name": "ETH",
          "percentage": 21,
          "color": "#627eea"
        }
      ],
      "currentInvested": 5.27,
      "timeRemaining": 220,
      "generatedAt": "2025-10-11T05:52:20.594538Z"
    },
    {
      "id": 9882,
      "name": "BTC/DOGE Bundle",
      "profit": "+16.2%",
      "duration": "14h",
      "risk": "High",
      "assets": [
        {
          "name": "BTC",
          "percentage": 26,
          "color": "#f7931a"
        },
        {
          "name": "DOGE",
          "percentage": 41,
          "color": "#d07c16"
        },
        {
          "name": "ADA",
          "percentage": 33,
          "color": "#0033ad"
        }
      ],
      "currentInvested": 12.31,
      "timeRemaining": 819,
      "generatedAt": "2025-10-11T05:52:20.594555Z"
    },
    {
      "id": 5039,
      "name": "BNB/ETH Bundle",
      "profit": "+14.8%",
      "duration": "1h",
      "risk": "High",
      "assets": [
        {
          "name": "BNB",
          "percentage": 33,
          "color": "#f3ba2f"
        },
        {
          "name": "ETH",
          "percentage": 27,
          "color": "#627eea"
        },
        {
          "name": "ADA",
          "percentage": 40,
          "color": "#0033ad"
        }
      ],
      "currentInvested": 9.28,
      "timeRemaining": 1599,
      "generatedAt": "2025-10-11T05:52:20.594572Z"
    },
    {
      "id": 5221,
      "name": "ADA/XRP Bundle",
      "profit": "+13.4%",
      "duration": "20h",
      "risk": "Low",
      "assets": [
        {
          "name": "ADA",
          "percentage": 41,
          "color": "#0033ad"
        },
        {
          "name": "XRP",
          "percentage": 31,
          "color": "#23292f"
        },
        {
          "name": "SHIB",
          "percentage": 28,
          "color": "#ffc000"
        }
      ],
      "currentInvested": 7.55,
      "timeRemaining": 97,
      "generatedAt": "2025-10-11T05:52:20.594589Z"
    }
  ]
}