{
  "lastUpdated": "2026-05-12T12:08:54.539040Z",
  "bundles": [
    {
      "id": 4266,
      "name": "DOGE/SHIB Bundle",
      "profit": "+6.1%",
      "duration": "1h",
      "risk": "Medium",
      "assets": [
        {
          "name": "DOGE",
          "percentage": 35,
          "color": "#d07c16"
        },
        {
          "name": "SHIB",
          "percentage": 33,
          "color": "#ffc000"
        },
        {
          "name": "SOL",
          "percentage": 32,
          "color": "#00d395"
        }
      ],
      "currentInvested": 10.21,
      "timeRemaining": 406,
      "generatedAt": "2026-05-12T12:08:54.538908Z"
    },
    {
      "id": 5343,
      "name": "DOGE/BTC Bundle",
      "profit": "+19.8%",
      "duration": "1h",
      "risk": "Low",
      "assets": [
        {
          "name": "DOGE",
          "percentage": 19,
          "color": "#d07c16"
        },
        {
          "name": "BTC",
          "percentage": 39,
          "color": "#f7931a"
        },
        {
          "name": "BNB",
          "percentage": 42,
          "color": "#f3ba2f"
        }
      ],
      "currentInvested": 3.79,
      "timeRemaining": 757,
      "generatedAt": "2026-05-12T12:08:54.538946Z"
    },
    {
      "id": 2695,
      "name": "DOT/BTC Bundle",
      "profit": "+12.0%",
      "duration": "19h",
      "risk": "High",
      "assets": [
        {
          "name": "DOT",
          "percentage": 22,
          "color": "#5d78ff"
        },
        {
          "name": "BTC",
          "percentage": 35,
          "color": "#f7931a"
        },
        {
          "name": "DOGE",
          "percentage": 43,
          "color": "#d07c16"
        }
      ],
      "currentInvested": 13.35,
      "timeRemaining": 644,
      "generatedAt": "2026-05-12T12:08:54.538973Z"
    },
    {
      "id": 1656,
      "name": "USDT/DOT Bundle",
      "profit": "+23.4%",
      "duration": "11h",
      "risk": "High",
      "assets": [
        {
          "name": "USDT",
          "percentage": 41,
          "color": "#26a17b"
        },
        {
          "name": "DOT",
          "percentage": 31,
          "color": "#5d78ff"
        },
        {
          "name": "SOL",
          "percentage": 28,
          "color": "#00d395"
        }
      ],
      "currentInvested": 2.73,
      "timeRemaining": 754,
      "generatedAt": "2026-05-12T12:08:54.538999Z"
    },
    {
      "id": 3510,
      "name": "ADA/SHIB Bundle",
      "profit": "+23.8%",
      "duration": "2h",
      "risk": "Low",
      "assets": [
        {
          "name": "ADA",
          "percentage": 37,
          "color": "#0033ad"
        },
        {
          "name": "SHIB",
          "percentage": 28,
          "color": "#ffc000"
        },
        {
          "name": "XRP",
          "percentage": 35,
          "color": "#23292f"
        }
      ],
      "currentInvested": 12.53,
      "timeRemaining": 679,
      "generatedAt": "2026-05-12T12:08:54.539021Z"
    },
    {
      "id": 4009,
      "name": "SOL/DOT Bundle",
      "profit": "+6.7%",
      "duration": "4h",
      "risk": "Medium",
      "assets": [
        {
          "name": "SOL",
          "percentage": 31,
          "color": "#00d395"
        },
        {
          "name": "DOT",
          "percentage": 34,
          "color": "#5d78ff"
        },
        {
          "name": "SHIB",
          "percentage": 35,
          "color": "#ffc000"
        }
      ],
      "currentInvested": 13.82,
      "timeRemaining": 117,
      "generatedAt": "2026-05-12T12:08:54.539038Z"
    }
  ]
}