{
  "lastUpdated": "2025-12-22T20:27:07.872516Z",
  "bundles": [
    {
      "id": 8750,
      "name": "ETH/ADA Bundle",
      "profit": "+13.9%",
      "duration": "12h",
      "risk": "Medium",
      "assets": [
        {
          "name": "ETH",
          "percentage": 29,
          "color": "#627eea"
        },
        {
          "name": "ADA",
          "percentage": 37,
          "color": "#0033ad"
        },
        {
          "name": "SOL",
          "percentage": 34,
          "color": "#00d395"
        }
      ],
      "currentInvested": 0.54,
      "timeRemaining": 1285,
      "generatedAt": "2025-12-22T20:27:07.872411Z"
    },
    {
      "id": 3344,
      "name": "BNB/DOT Bundle",
      "profit": "+20.9%",
      "duration": "19h",
      "risk": "Low",
      "assets": [
        {
          "name": "BNB",
          "percentage": 39,
          "color": "#f3ba2f"
        },
        {
          "name": "DOT",
          "percentage": 16,
          "color": "#5d78ff"
        },
        {
          "name": "ETH",
          "percentage": 45,
          "color": "#627eea"
        }
      ],
      "currentInvested": 2.67,
      "timeRemaining": 1732,
      "generatedAt": "2025-12-22T20:27:07.872440Z"
    },
    {
      "id": 2153,
      "name": "BNB/USDT Bundle",
      "profit": "+14.8%",
      "duration": "1h",
      "risk": "Low",
      "assets": [
        {
          "name": "BNB",
          "percentage": 20,
          "color": "#f3ba2f"
        },
        {
          "name": "USDT",
          "percentage": 28,
          "color": "#26a17b"
        },
        {
          "name": "DOGE",
          "percentage": 52,
          "color": "#d07c16"
        }
      ],
      "currentInvested": 7.42,
      "timeRemaining": 183,
      "generatedAt": "2025-12-22T20:27:07.872460Z"
    },
    {
      "id": 9873,
      "name": "BTC/DOT Bundle",
      "profit": "+10.7%",
      "duration": "12h",
      "risk": "High",
      "assets": [
        {
          "name": "BTC",
          "percentage": 27,
          "color": "#f7931a"
        },
        {
          "name": "DOT",
          "percentage": 18,
          "color": "#5d78ff"
        },
        {
          "name": "BNB",
          "percentage": 55,
          "color": "#f3ba2f"
        }
      ],
      "currentInvested": 12.51,
      "timeRemaining": 1138,
      "generatedAt": "2025-12-22T20:27:07.872479Z"
    },
    {
      "id": 9692,
      "name": "SOL/DOGE Bundle",
      "profit": "+25.4%",
      "duration": "9h",
      "risk": "Low",
      "assets": [
        {
          "name": "SOL",
          "percentage": 36,
          "color": "#00d395"
        },
        {
          "name": "DOGE",
          "percentage": 21,
          "color": "#d07c16"
        },
        {
          "name": "ETH",
          "percentage": 43,
          "color": "#627eea"
        }
      ],
      "currentInvested": 2.7,
      "timeRemaining": 701,
      "generatedAt": "2025-12-22T20:27:07.872496Z"
    },
    {
      "id": 9554,
      "name": "SOL/ETH Bundle",
      "profit": "+13.1%",
      "duration": "10h",
      "risk": "Low",
      "assets": [
        {
          "name": "SOL",
          "percentage": 26,
          "color": "#00d395"
        },
        {
          "name": "ETH",
          "percentage": 50,
          "color": "#627eea"
        },
        {
          "name": "BTC",
          "percentage": 24,
          "color": "#f7931a"
        }
      ],
      "currentInvested": 1.71,
      "timeRemaining": 1726,
      "generatedAt": "2025-12-22T20:27:07.872514Z"
    }
  ]
}