{
  "lastUpdated": "2026-01-29T05:51:26.473956Z",
  "bundles": [
    {
      "id": 5895,
      "name": "BTC/DOT Bundle",
      "profit": "+12.8%",
      "duration": "15h",
      "risk": "Medium",
      "assets": [
        {
          "name": "BTC",
          "percentage": 21,
          "color": "#f7931a"
        },
        {
          "name": "DOT",
          "percentage": 41,
          "color": "#5d78ff"
        },
        {
          "name": "DOGE",
          "percentage": 38,
          "color": "#d07c16"
        }
      ],
      "currentInvested": 2.37,
      "timeRemaining": 1371,
      "generatedAt": "2026-01-29T05:51:26.473871Z"
    },
    {
      "id": 8498,
      "name": "DOGE/SOL Bundle",
      "profit": "+23.9%",
      "duration": "19h",
      "risk": "High",
      "assets": [
        {
          "name": "DOGE",
          "percentage": 29,
          "color": "#d07c16"
        },
        {
          "name": "SOL",
          "percentage": 26,
          "color": "#00d395"
        },
        {
          "name": "ETH",
          "percentage": 45,
          "color": "#627eea"
        }
      ],
      "currentInvested": 12.97,
      "timeRemaining": 643,
      "generatedAt": "2026-01-29T05:51:26.473895Z"
    },
    {
      "id": 4294,
      "name": "SOL/ADA Bundle",
      "profit": "+25.2%",
      "duration": "13h",
      "risk": "High",
      "assets": [
        {
          "name": "SOL",
          "percentage": 16,
          "color": "#00d395"
        },
        {
          "name": "ADA",
          "percentage": 41,
          "color": "#0033ad"
        },
        {
          "name": "BTC",
          "percentage": 43,
          "color": "#f7931a"
        }
      ],
      "currentInvested": 2.47,
      "timeRemaining": 1102,
      "generatedAt": "2026-01-29T05:51:26.473910Z"
    },
    {
      "id": 3447,
      "name": "DOT/SHIB Bundle",
      "profit": "+17.1%",
      "duration": "21h",
      "risk": "Medium",
      "assets": [
        {
          "name": "DOT",
          "percentage": 41,
          "color": "#5d78ff"
        },
        {
          "name": "SHIB",
          "percentage": 31,
          "color": "#ffc000"
        },
        {
          "name": "XRP",
          "percentage": 28,
          "color": "#23292f"
        }
      ],
      "currentInvested": 3.91,
      "timeRemaining": 1641,
      "generatedAt": "2026-01-29T05:51:26.473926Z"
    },
    {
      "id": 9384,
      "name": "ETH/SOL Bundle",
      "profit": "+8.7%",
      "duration": "22h",
      "risk": "Medium",
      "assets": [
        {
          "name": "ETH",
          "percentage": 32,
          "color": "#627eea"
        },
        {
          "name": "SOL",
          "percentage": 37,
          "color": "#00d395"
        },
        {
          "name": "BNB",
          "percentage": 31,
          "color": "#f3ba2f"
        }
      ],
      "currentInvested": 7.11,
      "timeRemaining": 506,
      "generatedAt": "2026-01-29T05:51:26.473940Z"
    },
    {
      "id": 3861,
      "name": "ADA/BTC Bundle",
      "profit": "+5.1%",
      "duration": "1h",
      "risk": "High",
      "assets": [
        {
          "name": "ADA",
          "percentage": 35,
          "color": "#0033ad"
        },
        {
          "name": "BTC",
          "percentage": 37,
          "color": "#f7931a"
        },
        {
          "name": "SHIB",
          "percentage": 28,
          "color": "#ffc000"
        }
      ],
      "currentInvested": 4.46,
      "timeRemaining": 817,
      "generatedAt": "2026-01-29T05:51:26.473954Z"
    }
  ]
}