{
  "lastUpdated": "2025-12-25T11:55:34.021595Z",
  "bundles": [
    {
      "id": 8360,
      "name": "ADA/DOGE Bundle",
      "profit": "+8.2%",
      "duration": "24h",
      "risk": "Low",
      "assets": [
        {
          "name": "ADA",
          "percentage": 33,
          "color": "#0033ad"
        },
        {
          "name": "DOGE",
          "percentage": 31,
          "color": "#d07c16"
        },
        {
          "name": "SOL",
          "percentage": 36,
          "color": "#00d395"
        }
      ],
      "currentInvested": 9.45,
      "timeRemaining": 715,
      "generatedAt": "2025-12-25T11:55:34.021470Z"
    },
    {
      "id": 8156,
      "name": "XRP/ETH Bundle",
      "profit": "+12.8%",
      "duration": "15h",
      "risk": "Low",
      "assets": [
        {
          "name": "XRP",
          "percentage": 32,
          "color": "#23292f"
        },
        {
          "name": "ETH",
          "percentage": 35,
          "color": "#627eea"
        },
        {
          "name": "BTC",
          "percentage": 33,
          "color": "#f7931a"
        }
      ],
      "currentInvested": 0.01,
      "timeRemaining": 546,
      "generatedAt": "2025-12-25T11:55:34.021505Z"
    },
    {
      "id": 6407,
      "name": "ETH/BTC Bundle",
      "profit": "+6.4%",
      "duration": "15h",
      "risk": "Medium",
      "assets": [
        {
          "name": "ETH",
          "percentage": 25,
          "color": "#627eea"
        },
        {
          "name": "BTC",
          "percentage": 42,
          "color": "#f7931a"
        },
        {
          "name": "BNB",
          "percentage": 33,
          "color": "#f3ba2f"
        }
      ],
      "currentInvested": 5.43,
      "timeRemaining": 732,
      "generatedAt": "2025-12-25T11:55:34.021529Z"
    },
    {
      "id": 6279,
      "name": "ADA/XRP Bundle",
      "profit": "+23.8%",
      "duration": "19h",
      "risk": "High",
      "assets": [
        {
          "name": "ADA",
          "percentage": 38,
          "color": "#0033ad"
        },
        {
          "name": "XRP",
          "percentage": 36,
          "color": "#23292f"
        },
        {
          "name": "USDT",
          "percentage": 26,
          "color": "#26a17b"
        }
      ],
      "currentInvested": 5.91,
      "timeRemaining": 1470,
      "generatedAt": "2025-12-25T11:55:34.021551Z"
    },
    {
      "id": 2864,
      "name": "BNB/XRP Bundle",
      "profit": "+11.0%",
      "duration": "17h",
      "risk": "High",
      "assets": [
        {
          "name": "BNB",
          "percentage": 36,
          "color": "#f3ba2f"
        },
        {
          "name": "XRP",
          "percentage": 32,
          "color": "#23292f"
        },
        {
          "name": "DOT",
          "percentage": 32,
          "color": "#5d78ff"
        }
      ],
      "currentInvested": 9.79,
      "timeRemaining": 1657,
      "generatedAt": "2025-12-25T11:55:34.021573Z"
    },
    {
      "id": 4471,
      "name": "SOL/DOGE Bundle",
      "profit": "+14.1%",
      "duration": "4h",
      "risk": "Low",
      "assets": [
        {
          "name": "SOL",
          "percentage": 23,
          "color": "#00d395"
        },
        {
          "name": "DOGE",
          "percentage": 53,
          "color": "#d07c16"
        },
        {
          "name": "SHIB",
          "percentage": 24,
          "color": "#ffc000"
        }
      ],
      "currentInvested": 12.77,
      "timeRemaining": 1271,
      "generatedAt": "2025-12-25T11:55:34.021593Z"
    }
  ]
}