{
  "lastUpdated": "2026-07-16T10:27:38.064967Z",
  "bundles": [
    {
      "id": 6337,
      "name": "BTC/SHIB Bundle",
      "profit": "+9.1%",
      "duration": "2h",
      "risk": "Low",
      "assets": [
        {
          "name": "BTC",
          "percentage": 27,
          "color": "#f7931a"
        },
        {
          "name": "SHIB",
          "percentage": 21,
          "color": "#ffc000"
        },
        {
          "name": "USDT",
          "percentage": 52,
          "color": "#26a17b"
        }
      ],
      "currentInvested": 11.76,
      "timeRemaining": 359,
      "generatedAt": "2026-07-16T10:27:38.064902Z"
    },
    {
      "id": 2216,
      "name": "ETH/DOT Bundle",
      "profit": "+19.5%",
      "duration": "19h",
      "risk": "Medium",
      "assets": [
        {
          "name": "ETH",
          "percentage": 43,
          "color": "#627eea"
        },
        {
          "name": "DOT",
          "percentage": 19,
          "color": "#5d78ff"
        },
        {
          "name": "BNB",
          "percentage": 38,
          "color": "#f3ba2f"
        }
      ],
      "currentInvested": 2.36,
      "timeRemaining": 1568,
      "generatedAt": "2026-07-16T10:27:38.064925Z"
    },
    {
      "id": 2657,
      "name": "BTC/ADA Bundle",
      "profit": "+17.7%",
      "duration": "22h",
      "risk": "Low",
      "assets": [
        {
          "name": "BTC",
          "percentage": 36,
          "color": "#f7931a"
        },
        {
          "name": "ADA",
          "percentage": 31,
          "color": "#0033ad"
        },
        {
          "name": "ETH",
          "percentage": 33,
          "color": "#627eea"
        }
      ],
      "currentInvested": 9.48,
      "timeRemaining": 583,
      "generatedAt": "2026-07-16T10:27:38.064935Z"
    },
    {
      "id": 3588,
      "name": "BTC/ETH Bundle",
      "profit": "+22.4%",
      "duration": "1h",
      "risk": "High",
      "assets": [
        {
          "name": "BTC",
          "percentage": 45,
          "color": "#f7931a"
        },
        {
          "name": "ETH",
          "percentage": 22,
          "color": "#627eea"
        },
        {
          "name": "DOGE",
          "percentage": 33,
          "color": "#d07c16"
        }
      ],
      "currentInvested": 5.39,
      "timeRemaining": 1215,
      "generatedAt": "2026-07-16T10:27:38.064946Z"
    },
    {
      "id": 5190,
      "name": "SHIB/USDT Bundle",
      "profit": "+17.3%",
      "duration": "1h",
      "risk": "Low",
      "assets": [
        {
          "name": "SHIB",
          "percentage": 17,
          "color": "#ffc000"
        },
        {
          "name": "USDT",
          "percentage": 32,
          "color": "#26a17b"
        },
        {
          "name": "DOGE",
          "percentage": 51,
          "color": "#d07c16"
        }
      ],
      "currentInvested": 6.27,
      "timeRemaining": 1347,
      "generatedAt": "2026-07-16T10:27:38.064956Z"
    },
    {
      "id": 2106,
      "name": "DOGE/BTC Bundle",
      "profit": "+18.5%",
      "duration": "12h",
      "risk": "High",
      "assets": [
        {
          "name": "DOGE",
          "percentage": 33,
          "color": "#d07c16"
        },
        {
          "name": "BTC",
          "percentage": 32,
          "color": "#f7931a"
        },
        {
          "name": "DOT",
          "percentage": 35,
          "color": "#5d78ff"
        }
      ],
      "currentInvested": 5.16,
      "timeRemaining": 683,
      "generatedAt": "2026-07-16T10:27:38.064966Z"
    }
  ]
}