{
  "lastUpdated": "2025-11-20T13:57:01.316520Z",
  "bundles": [
    {
      "id": 9894,
      "name": "ADA/BTC Bundle",
      "profit": "+23.7%",
      "duration": "22h",
      "risk": "Medium",
      "assets": [
        {
          "name": "ADA",
          "percentage": 37,
          "color": "#0033ad"
        },
        {
          "name": "BTC",
          "percentage": 39,
          "color": "#f7931a"
        },
        {
          "name": "BNB",
          "percentage": 24,
          "color": "#f3ba2f"
        }
      ],
      "currentInvested": 0.63,
      "timeRemaining": 713,
      "generatedAt": "2025-11-20T13:57:01.316417Z"
    },
    {
      "id": 7647,
      "name": "SHIB/SOL Bundle",
      "profit": "+9.2%",
      "duration": "9h",
      "risk": "High",
      "assets": [
        {
          "name": "SHIB",
          "percentage": 26,
          "color": "#ffc000"
        },
        {
          "name": "SOL",
          "percentage": 54,
          "color": "#00d395"
        },
        {
          "name": "DOGE",
          "percentage": 20,
          "color": "#d07c16"
        }
      ],
      "currentInvested": 0.43,
      "timeRemaining": 1274,
      "generatedAt": "2025-11-20T13:57:01.316447Z"
    },
    {
      "id": 5881,
      "name": "XRP/ADA Bundle",
      "profit": "+11.8%",
      "duration": "4h",
      "risk": "Low",
      "assets": [
        {
          "name": "XRP",
          "percentage": 40,
          "color": "#23292f"
        },
        {
          "name": "ADA",
          "percentage": 25,
          "color": "#0033ad"
        },
        {
          "name": "SHIB",
          "percentage": 35,
          "color": "#ffc000"
        }
      ],
      "currentInvested": 5.54,
      "timeRemaining": 843,
      "generatedAt": "2025-11-20T13:57:01.316467Z"
    },
    {
      "id": 3417,
      "name": "BNB/SOL Bundle",
      "profit": "+6.2%",
      "duration": "5h",
      "risk": "Medium",
      "assets": [
        {
          "name": "BNB",
          "percentage": 24,
          "color": "#f3ba2f"
        },
        {
          "name": "SOL",
          "percentage": 43,
          "color": "#00d395"
        },
        {
          "name": "ADA",
          "percentage": 33,
          "color": "#0033ad"
        }
      ],
      "currentInvested": 7.93,
      "timeRemaining": 1527,
      "generatedAt": "2025-11-20T13:57:01.316485Z"
    },
    {
      "id": 8314,
      "name": "BNB/SHIB Bundle",
      "profit": "+6.3%",
      "duration": "21h",
      "risk": "Medium",
      "assets": [
        {
          "name": "BNB",
          "percentage": 34,
          "color": "#f3ba2f"
        },
        {
          "name": "SHIB",
          "percentage": 21,
          "color": "#ffc000"
        },
        {
          "name": "ADA",
          "percentage": 45,
          "color": "#0033ad"
        }
      ],
      "currentInvested": 10.06,
      "timeRemaining": 1099,
      "generatedAt": "2025-11-20T13:57:01.316502Z"
    },
    {
      "id": 2804,
      "name": "BTC/SOL Bundle",
      "profit": "+23.8%",
      "duration": "18h",
      "risk": "Medium",
      "assets": [
        {
          "name": "BTC",
          "percentage": 37,
          "color": "#f7931a"
        },
        {
          "name": "SOL",
          "percentage": 40,
          "color": "#00d395"
        },
        {
          "name": "ADA",
          "percentage": 23,
          "color": "#0033ad"
        }
      ],
      "currentInvested": 3.25,
      "timeRemaining": 67,
      "generatedAt": "2025-11-20T13:57:01.316518Z"
    }
  ]
}