{
  "lastUpdated": "2026-03-21T22:59:44.597270Z",
  "bundles": [
    {
      "id": 3737,
      "name": "BTC/SHIB Bundle",
      "profit": "+12.5%",
      "duration": "14h",
      "risk": "Low",
      "assets": [
        {
          "name": "BTC",
          "percentage": 37,
          "color": "#f7931a"
        },
        {
          "name": "SHIB",
          "percentage": 34,
          "color": "#ffc000"
        },
        {
          "name": "XRP",
          "percentage": 29,
          "color": "#23292f"
        }
      ],
      "currentInvested": 2.93,
      "timeRemaining": 1420,
      "generatedAt": "2026-03-21T22:59:44.597168Z"
    },
    {
      "id": 5607,
      "name": "ETH/BNB Bundle",
      "profit": "+14.8%",
      "duration": "17h",
      "risk": "Medium",
      "assets": [
        {
          "name": "ETH",
          "percentage": 30,
          "color": "#627eea"
        },
        {
          "name": "BNB",
          "percentage": 16,
          "color": "#f3ba2f"
        },
        {
          "name": "SOL",
          "percentage": 54,
          "color": "#00d395"
        }
      ],
      "currentInvested": 13.37,
      "timeRemaining": 782,
      "generatedAt": "2026-03-21T22:59:44.597195Z"
    },
    {
      "id": 7258,
      "name": "ETH/SHIB Bundle",
      "profit": "+6.3%",
      "duration": "22h",
      "risk": "High",
      "assets": [
        {
          "name": "ETH",
          "percentage": 47,
          "color": "#627eea"
        },
        {
          "name": "SHIB",
          "percentage": 16,
          "color": "#ffc000"
        },
        {
          "name": "ADA",
          "percentage": 37,
          "color": "#0033ad"
        }
      ],
      "currentInvested": 13.76,
      "timeRemaining": 1145,
      "generatedAt": "2026-03-21T22:59:44.597214Z"
    },
    {
      "id": 8816,
      "name": "ADA/ETH Bundle",
      "profit": "+11.7%",
      "duration": "7h",
      "risk": "Medium",
      "assets": [
        {
          "name": "ADA",
          "percentage": 24,
          "color": "#0033ad"
        },
        {
          "name": "ETH",
          "percentage": 36,
          "color": "#627eea"
        },
        {
          "name": "XRP",
          "percentage": 40,
          "color": "#23292f"
        }
      ],
      "currentInvested": 6.6,
      "timeRemaining": 1105,
      "generatedAt": "2026-03-21T22:59:44.597233Z"
    },
    {
      "id": 9097,
      "name": "SOL/ETH Bundle",
      "profit": "+21.9%",
      "duration": "23h",
      "risk": "Medium",
      "assets": [
        {
          "name": "SOL",
          "percentage": 18,
          "color": "#00d395"
        },
        {
          "name": "ETH",
          "percentage": 54,
          "color": "#627eea"
        },
        {
          "name": "SHIB",
          "percentage": 28,
          "color": "#ffc000"
        }
      ],
      "currentInvested": 8.32,
      "timeRemaining": 763,
      "generatedAt": "2026-03-21T22:59:44.597252Z"
    },
    {
      "id": 8458,
      "name": "DOT/ETH Bundle",
      "profit": "+16.9%",
      "duration": "7h",
      "risk": "Medium",
      "assets": [
        {
          "name": "DOT",
          "percentage": 16,
          "color": "#5d78ff"
        },
        {
          "name": "ETH",
          "percentage": 52,
          "color": "#627eea"
        },
        {
          "name": "BTC",
          "percentage": 32,
          "color": "#f7931a"
        }
      ],
      "currentInvested": 3.69,
      "timeRemaining": 1779,
      "generatedAt": "2026-03-21T22:59:44.597269Z"
    }
  ]
}