{
  "lastUpdated": "2025-08-21T14:47:35.466189Z",
  "bundles": [
    {
      "id": 4267,
      "name": "DOT/SHIB Bundle",
      "profit": "+9.0%",
      "duration": "15h",
      "risk": "Low",
      "assets": [
        {
          "name": "DOT",
          "percentage": 21,
          "color": "#5d78ff"
        },
        {
          "name": "SHIB",
          "percentage": 39,
          "color": "#ffc000"
        },
        {
          "name": "ADA",
          "percentage": 40,
          "color": "#0033ad"
        }
      ],
      "currentInvested": 1.24,
      "timeRemaining": 135,
      "generatedAt": "2025-08-21T14:47:35.466085Z"
    },
    {
      "id": 4579,
      "name": "DOT/ETH Bundle",
      "profit": "+15.7%",
      "duration": "19h",
      "risk": "Medium",
      "assets": [
        {
          "name": "DOT",
          "percentage": 40,
          "color": "#5d78ff"
        },
        {
          "name": "ETH",
          "percentage": 27,
          "color": "#627eea"
        },
        {
          "name": "SOL",
          "percentage": 33,
          "color": "#00d395"
        }
      ],
      "currentInvested": 11.89,
      "timeRemaining": 1686,
      "generatedAt": "2025-08-21T14:47:35.466115Z"
    },
    {
      "id": 3554,
      "name": "DOGE/USDT Bundle",
      "profit": "+10.1%",
      "duration": "20h",
      "risk": "Medium",
      "assets": [
        {
          "name": "DOGE",
          "percentage": 38,
          "color": "#d07c16"
        },
        {
          "name": "USDT",
          "percentage": 35,
          "color": "#26a17b"
        },
        {
          "name": "BNB",
          "percentage": 27,
          "color": "#f3ba2f"
        }
      ],
      "currentInvested": 8.15,
      "timeRemaining": 1397,
      "generatedAt": "2025-08-21T14:47:35.466134Z"
    },
    {
      "id": 9500,
      "name": "DOGE/ETH Bundle",
      "profit": "+17.9%",
      "duration": "9h",
      "risk": "High",
      "assets": [
        {
          "name": "DOGE",
          "percentage": 35,
          "color": "#d07c16"
        },
        {
          "name": "ETH",
          "percentage": 29,
          "color": "#627eea"
        },
        {
          "name": "DOT",
          "percentage": 36,
          "color": "#5d78ff"
        }
      ],
      "currentInvested": 0.23,
      "timeRemaining": 1068,
      "generatedAt": "2025-08-21T14:47:35.466152Z"
    },
    {
      "id": 4355,
      "name": "SHIB/DOT Bundle",
      "profit": "+14.6%",
      "duration": "18h",
      "risk": "Low",
      "assets": [
        {
          "name": "SHIB",
          "percentage": 41,
          "color": "#ffc000"
        },
        {
          "name": "DOT",
          "percentage": 34,
          "color": "#5d78ff"
        },
        {
          "name": "USDT",
          "percentage": 25,
          "color": "#26a17b"
        }
      ],
      "currentInvested": 6.28,
      "timeRemaining": 919,
      "generatedAt": "2025-08-21T14:47:35.466170Z"
    },
    {
      "id": 1802,
      "name": "SHIB/ETH Bundle",
      "profit": "+13.3%",
      "duration": "9h",
      "risk": "High",
      "assets": [
        {
          "name": "SHIB",
          "percentage": 47,
          "color": "#ffc000"
        },
        {
          "name": "ETH",
          "percentage": 19,
          "color": "#627eea"
        },
        {
          "name": "SOL",
          "percentage": 34,
          "color": "#00d395"
        }
      ],
      "currentInvested": 8.27,
      "timeRemaining": 443,
      "generatedAt": "2025-08-21T14:47:35.466187Z"
    }
  ]
}