{
  "lastUpdated": "2026-03-09T23:36:17.949105Z",
  "bundles": [
    {
      "id": 8462,
      "name": "SHIB/DOGE Bundle",
      "profit": "+25.6%",
      "duration": "5h",
      "risk": "High",
      "assets": [
        {
          "name": "SHIB",
          "percentage": 37,
          "color": "#ffc000"
        },
        {
          "name": "DOGE",
          "percentage": 25,
          "color": "#d07c16"
        },
        {
          "name": "DOT",
          "percentage": 38,
          "color": "#5d78ff"
        }
      ],
      "currentInvested": 7.29,
      "timeRemaining": 1647,
      "generatedAt": "2026-03-09T23:36:17.949000Z"
    },
    {
      "id": 5978,
      "name": "DOGE/XRP Bundle",
      "profit": "+15.1%",
      "duration": "2h",
      "risk": "Medium",
      "assets": [
        {
          "name": "DOGE",
          "percentage": 16,
          "color": "#d07c16"
        },
        {
          "name": "XRP",
          "percentage": 50,
          "color": "#23292f"
        },
        {
          "name": "BTC",
          "percentage": 34,
          "color": "#f7931a"
        }
      ],
      "currentInvested": 7.44,
      "timeRemaining": 1683,
      "generatedAt": "2026-03-09T23:36:17.949028Z"
    },
    {
      "id": 8246,
      "name": "BNB/ETH Bundle",
      "profit": "+20.1%",
      "duration": "4h",
      "risk": "Medium",
      "assets": [
        {
          "name": "BNB",
          "percentage": 30,
          "color": "#f3ba2f"
        },
        {
          "name": "ETH",
          "percentage": 31,
          "color": "#627eea"
        },
        {
          "name": "XRP",
          "percentage": 39,
          "color": "#23292f"
        }
      ],
      "currentInvested": 10.66,
      "timeRemaining": 450,
      "generatedAt": "2026-03-09T23:36:17.949050Z"
    },
    {
      "id": 5996,
      "name": "ADA/ETH Bundle",
      "profit": "+25.5%",
      "duration": "16h",
      "risk": "Low",
      "assets": [
        {
          "name": "ADA",
          "percentage": 21,
          "color": "#0033ad"
        },
        {
          "name": "ETH",
          "percentage": 42,
          "color": "#627eea"
        },
        {
          "name": "SHIB",
          "percentage": 37,
          "color": "#ffc000"
        }
      ],
      "currentInvested": 2.8,
      "timeRemaining": 1531,
      "generatedAt": "2026-03-09T23:36:17.949070Z"
    },
    {
      "id": 1409,
      "name": "SOL/USDT Bundle",
      "profit": "+23.9%",
      "duration": "16h",
      "risk": "Low",
      "assets": [
        {
          "name": "SOL",
          "percentage": 45,
          "color": "#00d395"
        },
        {
          "name": "USDT",
          "percentage": 29,
          "color": "#26a17b"
        },
        {
          "name": "ADA",
          "percentage": 26,
          "color": "#0033ad"
        }
      ],
      "currentInvested": 1.36,
      "timeRemaining": 1080,
      "generatedAt": "2026-03-09T23:36:17.949087Z"
    },
    {
      "id": 6302,
      "name": "BNB/DOT Bundle",
      "profit": "+8.6%",
      "duration": "1h",
      "risk": "High",
      "assets": [
        {
          "name": "BNB",
          "percentage": 32,
          "color": "#f3ba2f"
        },
        {
          "name": "DOT",
          "percentage": 45,
          "color": "#5d78ff"
        },
        {
          "name": "ADA",
          "percentage": 23,
          "color": "#0033ad"
        }
      ],
      "currentInvested": 10.14,
      "timeRemaining": 707,
      "generatedAt": "2026-03-09T23:36:17.949103Z"
    }
  ]
}