{
  "lastUpdated": "2025-08-28T23:44:51.263365Z",
  "bundles": [
    {
      "id": 4935,
      "name": "BTC/SOL Bundle",
      "profit": "+23.3%",
      "duration": "19h",
      "risk": "Medium",
      "assets": [
        {
          "name": "BTC",
          "percentage": 17,
          "color": "#f7931a"
        },
        {
          "name": "SOL",
          "percentage": 49,
          "color": "#00d395"
        },
        {
          "name": "XRP",
          "percentage": 34,
          "color": "#23292f"
        }
      ],
      "currentInvested": 0.93,
      "timeRemaining": 221,
      "generatedAt": "2025-08-28T23:44:51.263205Z"
    },
    {
      "id": 9054,
      "name": "DOT/SHIB Bundle",
      "profit": "+11.4%",
      "duration": "23h",
      "risk": "Low",
      "assets": [
        {
          "name": "DOT",
          "percentage": 19,
          "color": "#5d78ff"
        },
        {
          "name": "SHIB",
          "percentage": 54,
          "color": "#ffc000"
        },
        {
          "name": "BNB",
          "percentage": 27,
          "color": "#f3ba2f"
        }
      ],
      "currentInvested": 8.23,
      "timeRemaining": 994,
      "generatedAt": "2025-08-28T23:44:51.263272Z"
    },
    {
      "id": 7326,
      "name": "DOGE/ETH Bundle",
      "profit": "+9.5%",
      "duration": "15h",
      "risk": "Low",
      "assets": [
        {
          "name": "DOGE",
          "percentage": 42,
          "color": "#d07c16"
        },
        {
          "name": "ETH",
          "percentage": 35,
          "color": "#627eea"
        },
        {
          "name": "BNB",
          "percentage": 23,
          "color": "#f3ba2f"
        }
      ],
      "currentInvested": 14.05,
      "timeRemaining": 167,
      "generatedAt": "2025-08-28T23:44:51.263297Z"
    },
    {
      "id": 7342,
      "name": "DOGE/USDT Bundle",
      "profit": "+6.1%",
      "duration": "6h",
      "risk": "Low",
      "assets": [
        {
          "name": "DOGE",
          "percentage": 40,
          "color": "#d07c16"
        },
        {
          "name": "USDT",
          "percentage": 35,
          "color": "#26a17b"
        },
        {
          "name": "SOL",
          "percentage": 25,
          "color": "#00d395"
        }
      ],
      "currentInvested": 7.42,
      "timeRemaining": 1258,
      "generatedAt": "2025-08-28T23:44:51.263320Z"
    },
    {
      "id": 2690,
      "name": "XRP/SHIB Bundle",
      "profit": "+8.6%",
      "duration": "9h",
      "risk": "Medium",
      "assets": [
        {
          "name": "XRP",
          "percentage": 47,
          "color": "#23292f"
        },
        {
          "name": "SHIB",
          "percentage": 19,
          "color": "#ffc000"
        },
        {
          "name": "SOL",
          "percentage": 34,
          "color": "#00d395"
        }
      ],
      "currentInvested": 13.79,
      "timeRemaining": 1235,
      "generatedAt": "2025-08-28T23:44:51.263342Z"
    },
    {
      "id": 8461,
      "name": "DOT/XRP Bundle",
      "profit": "+17.4%",
      "duration": "21h",
      "risk": "Medium",
      "assets": [
        {
          "name": "DOT",
          "percentage": 36,
          "color": "#5d78ff"
        },
        {
          "name": "XRP",
          "percentage": 39,
          "color": "#23292f"
        },
        {
          "name": "SOL",
          "percentage": 25,
          "color": "#00d395"
        }
      ],
      "currentInvested": 8.41,
      "timeRemaining": 1519,
      "generatedAt": "2025-08-28T23:44:51.263363Z"
    }
  ]
}