{
  "lastUpdated": "2026-06-27T07:26:55.243844Z",
  "bundles": [
    {
      "id": 8283,
      "name": "ETH/ADA Bundle",
      "profit": "+8.5%",
      "duration": "19h",
      "risk": "Low",
      "assets": [
        {
          "name": "ETH",
          "percentage": 33,
          "color": "#627eea"
        },
        {
          "name": "ADA",
          "percentage": 30,
          "color": "#0033ad"
        },
        {
          "name": "SHIB",
          "percentage": 37,
          "color": "#ffc000"
        }
      ],
      "currentInvested": 10.82,
      "timeRemaining": 1084,
      "generatedAt": "2026-06-27T07:26:55.243744Z"
    },
    {
      "id": 1529,
      "name": "USDT/DOT Bundle",
      "profit": "+17.5%",
      "duration": "17h",
      "risk": "Medium",
      "assets": [
        {
          "name": "USDT",
          "percentage": 41,
          "color": "#26a17b"
        },
        {
          "name": "DOT",
          "percentage": 28,
          "color": "#5d78ff"
        },
        {
          "name": "ADA",
          "percentage": 31,
          "color": "#0033ad"
        }
      ],
      "currentInvested": 7.16,
      "timeRemaining": 123,
      "generatedAt": "2026-06-27T07:26:55.243771Z"
    },
    {
      "id": 5844,
      "name": "XRP/BNB Bundle",
      "profit": "+23.0%",
      "duration": "3h",
      "risk": "Medium",
      "assets": [
        {
          "name": "XRP",
          "percentage": 33,
          "color": "#23292f"
        },
        {
          "name": "BNB",
          "percentage": 48,
          "color": "#f3ba2f"
        },
        {
          "name": "ETH",
          "percentage": 19,
          "color": "#627eea"
        }
      ],
      "currentInvested": 0.68,
      "timeRemaining": 1582,
      "generatedAt": "2026-06-27T07:26:55.243790Z"
    },
    {
      "id": 9475,
      "name": "ADA/USDT Bundle",
      "profit": "+5.3%",
      "duration": "11h",
      "risk": "Low",
      "assets": [
        {
          "name": "ADA",
          "percentage": 25,
          "color": "#0033ad"
        },
        {
          "name": "USDT",
          "percentage": 28,
          "color": "#26a17b"
        },
        {
          "name": "BTC",
          "percentage": 47,
          "color": "#f7931a"
        }
      ],
      "currentInvested": 14.24,
      "timeRemaining": 1238,
      "generatedAt": "2026-06-27T07:26:55.243807Z"
    },
    {
      "id": 7219,
      "name": "SHIB/ADA Bundle",
      "profit": "+18.0%",
      "duration": "2h",
      "risk": "Medium",
      "assets": [
        {
          "name": "SHIB",
          "percentage": 36,
          "color": "#ffc000"
        },
        {
          "name": "ADA",
          "percentage": 16,
          "color": "#0033ad"
        },
        {
          "name": "XRP",
          "percentage": 48,
          "color": "#23292f"
        }
      ],
      "currentInvested": 13.82,
      "timeRemaining": 1458,
      "generatedAt": "2026-06-27T07:26:55.243824Z"
    },
    {
      "id": 6650,
      "name": "SOL/ADA Bundle",
      "profit": "+24.0%",
      "duration": "13h",
      "risk": "Medium",
      "assets": [
        {
          "name": "SOL",
          "percentage": 35,
          "color": "#00d395"
        },
        {
          "name": "ADA",
          "percentage": 35,
          "color": "#0033ad"
        },
        {
          "name": "DOGE",
          "percentage": 30,
          "color": "#d07c16"
        }
      ],
      "currentInvested": 0.82,
      "timeRemaining": 1560,
      "generatedAt": "2026-06-27T07:26:55.243842Z"
    }
  ]
}