{
  "lastUpdated": "2025-12-12T15:59:23.245164Z",
  "bundles": [
    {
      "id": 8099,
      "name": "XRP/ETH Bundle",
      "profit": "+20.9%",
      "duration": "18h",
      "risk": "Medium",
      "assets": [
        {
          "name": "XRP",
          "percentage": 39,
          "color": "#23292f"
        },
        {
          "name": "ETH",
          "percentage": 31,
          "color": "#627eea"
        },
        {
          "name": "SOL",
          "percentage": 30,
          "color": "#00d395"
        }
      ],
      "currentInvested": 0.44,
      "timeRemaining": 692,
      "generatedAt": "2025-12-12T15:59:23.245059Z"
    },
    {
      "id": 2089,
      "name": "ETH/DOT Bundle",
      "profit": "+7.1%",
      "duration": "13h",
      "risk": "High",
      "assets": [
        {
          "name": "ETH",
          "percentage": 20,
          "color": "#627eea"
        },
        {
          "name": "DOT",
          "percentage": 40,
          "color": "#5d78ff"
        },
        {
          "name": "ADA",
          "percentage": 40,
          "color": "#0033ad"
        }
      ],
      "currentInvested": 11.86,
      "timeRemaining": 264,
      "generatedAt": "2025-12-12T15:59:23.245087Z"
    },
    {
      "id": 1416,
      "name": "DOGE/BTC Bundle",
      "profit": "+8.5%",
      "duration": "21h",
      "risk": "High",
      "assets": [
        {
          "name": "DOGE",
          "percentage": 21,
          "color": "#d07c16"
        },
        {
          "name": "BTC",
          "percentage": 38,
          "color": "#f7931a"
        },
        {
          "name": "ADA",
          "percentage": 41,
          "color": "#0033ad"
        }
      ],
      "currentInvested": 13.46,
      "timeRemaining": 635,
      "generatedAt": "2025-12-12T15:59:23.245108Z"
    },
    {
      "id": 3985,
      "name": "XRP/SOL Bundle",
      "profit": "+19.6%",
      "duration": "21h",
      "risk": "Medium",
      "assets": [
        {
          "name": "XRP",
          "percentage": 36,
          "color": "#23292f"
        },
        {
          "name": "SOL",
          "percentage": 22,
          "color": "#00d395"
        },
        {
          "name": "ETH",
          "percentage": 42,
          "color": "#627eea"
        }
      ],
      "currentInvested": 10.5,
      "timeRemaining": 950,
      "generatedAt": "2025-12-12T15:59:23.245127Z"
    },
    {
      "id": 6604,
      "name": "USDT/SHIB Bundle",
      "profit": "+11.5%",
      "duration": "24h",
      "risk": "Low",
      "assets": [
        {
          "name": "USDT",
          "percentage": 17,
          "color": "#26a17b"
        },
        {
          "name": "SHIB",
          "percentage": 41,
          "color": "#ffc000"
        },
        {
          "name": "SOL",
          "percentage": 42,
          "color": "#00d395"
        }
      ],
      "currentInvested": 10.93,
      "timeRemaining": 1639,
      "generatedAt": "2025-12-12T15:59:23.245145Z"
    },
    {
      "id": 3297,
      "name": "XRP/ADA Bundle",
      "profit": "+22.5%",
      "duration": "19h",
      "risk": "Low",
      "assets": [
        {
          "name": "XRP",
          "percentage": 28,
          "color": "#23292f"
        },
        {
          "name": "ADA",
          "percentage": 40,
          "color": "#0033ad"
        },
        {
          "name": "DOGE",
          "percentage": 32,
          "color": "#d07c16"
        }
      ],
      "currentInvested": 7.87,
      "timeRemaining": 460,
      "generatedAt": "2025-12-12T15:59:23.245162Z"
    }
  ]
}