{
  "lastUpdated": "2026-05-18T21:52:01.019015Z",
  "bundles": [
    {
      "id": 3076,
      "name": "BNB/XRP Bundle",
      "profit": "+16.0%",
      "duration": "2h",
      "risk": "High",
      "assets": [
        {
          "name": "BNB",
          "percentage": 36,
          "color": "#f3ba2f"
        },
        {
          "name": "XRP",
          "percentage": 39,
          "color": "#23292f"
        },
        {
          "name": "DOGE",
          "percentage": 25,
          "color": "#d07c16"
        }
      ],
      "currentInvested": 5.18,
      "timeRemaining": 1144,
      "generatedAt": "2026-05-18T21:52:01.018840Z"
    },
    {
      "id": 1784,
      "name": "BTC/DOT Bundle",
      "profit": "+25.3%",
      "duration": "14h",
      "risk": "Low",
      "assets": [
        {
          "name": "BTC",
          "percentage": 21,
          "color": "#f7931a"
        },
        {
          "name": "DOT",
          "percentage": 40,
          "color": "#5d78ff"
        },
        {
          "name": "USDT",
          "percentage": 39,
          "color": "#26a17b"
        }
      ],
      "currentInvested": 3.4,
      "timeRemaining": 1518,
      "generatedAt": "2026-05-18T21:52:01.018876Z"
    },
    {
      "id": 8459,
      "name": "ADA/DOGE Bundle",
      "profit": "+13.5%",
      "duration": "9h",
      "risk": "Medium",
      "assets": [
        {
          "name": "ADA",
          "percentage": 32,
          "color": "#0033ad"
        },
        {
          "name": "DOGE",
          "percentage": 36,
          "color": "#d07c16"
        },
        {
          "name": "USDT",
          "percentage": 32,
          "color": "#26a17b"
        }
      ],
      "currentInvested": 12.8,
      "timeRemaining": 865,
      "generatedAt": "2026-05-18T21:52:01.018940Z"
    },
    {
      "id": 3267,
      "name": "XRP/ADA Bundle",
      "profit": "+6.2%",
      "duration": "16h",
      "risk": "High",
      "assets": [
        {
          "name": "XRP",
          "percentage": 36,
          "color": "#23292f"
        },
        {
          "name": "ADA",
          "percentage": 15,
          "color": "#0033ad"
        },
        {
          "name": "DOT",
          "percentage": 49,
          "color": "#5d78ff"
        }
      ],
      "currentInvested": 13.11,
      "timeRemaining": 1623,
      "generatedAt": "2026-05-18T21:52:01.018969Z"
    },
    {
      "id": 4073,
      "name": "BNB/DOGE Bundle",
      "profit": "+8.7%",
      "duration": "13h",
      "risk": "High",
      "assets": [
        {
          "name": "BNB",
          "percentage": 45,
          "color": "#f3ba2f"
        },
        {
          "name": "DOGE",
          "percentage": 38,
          "color": "#d07c16"
        },
        {
          "name": "ADA",
          "percentage": 17,
          "color": "#0033ad"
        }
      ],
      "currentInvested": 4.24,
      "timeRemaining": 931,
      "generatedAt": "2026-05-18T21:52:01.018992Z"
    },
    {
      "id": 3903,
      "name": "BTC/USDT Bundle",
      "profit": "+13.9%",
      "duration": "21h",
      "risk": "Low",
      "assets": [
        {
          "name": "BTC",
          "percentage": 32,
          "color": "#f7931a"
        },
        {
          "name": "USDT",
          "percentage": 41,
          "color": "#26a17b"
        },
        {
          "name": "ADA",
          "percentage": 27,
          "color": "#0033ad"
        }
      ],
      "currentInvested": 13.36,
      "timeRemaining": 1218,
      "generatedAt": "2026-05-18T21:52:01.019013Z"
    }
  ]
}