{
  "lastUpdated": "2025-08-16T13:02:05.930070Z",
  "bundles": [
    {
      "id": 9495,
      "name": "SHIB/XRP Bundle",
      "profit": "+7.1%",
      "duration": "8h",
      "risk": "High",
      "assets": [
        {
          "name": "SHIB",
          "percentage": 46,
          "color": "#ffc000"
        },
        {
          "name": "XRP",
          "percentage": 32,
          "color": "#23292f"
        },
        {
          "name": "SOL",
          "percentage": 22,
          "color": "#00d395"
        }
      ],
      "currentInvested": 9.3,
      "timeRemaining": 1067,
      "generatedAt": "2025-08-16T13:02:05.929965Z"
    },
    {
      "id": 3826,
      "name": "ETH/BTC Bundle",
      "profit": "+16.2%",
      "duration": "3h",
      "risk": "High",
      "assets": [
        {
          "name": "ETH",
          "percentage": 34,
          "color": "#627eea"
        },
        {
          "name": "BTC",
          "percentage": 38,
          "color": "#f7931a"
        },
        {
          "name": "XRP",
          "percentage": 28,
          "color": "#23292f"
        }
      ],
      "currentInvested": 5.73,
      "timeRemaining": 1022,
      "generatedAt": "2025-08-16T13:02:05.929994Z"
    },
    {
      "id": 2842,
      "name": "DOGE/XRP Bundle",
      "profit": "+22.8%",
      "duration": "23h",
      "risk": "Low",
      "assets": [
        {
          "name": "DOGE",
          "percentage": 32,
          "color": "#d07c16"
        },
        {
          "name": "XRP",
          "percentage": 41,
          "color": "#23292f"
        },
        {
          "name": "SOL",
          "percentage": 27,
          "color": "#00d395"
        }
      ],
      "currentInvested": 2.48,
      "timeRemaining": 1441,
      "generatedAt": "2025-08-16T13:02:05.930014Z"
    },
    {
      "id": 7411,
      "name": "DOT/DOGE Bundle",
      "profit": "+19.7%",
      "duration": "17h",
      "risk": "High",
      "assets": [
        {
          "name": "DOT",
          "percentage": 38,
          "color": "#5d78ff"
        },
        {
          "name": "DOGE",
          "percentage": 26,
          "color": "#d07c16"
        },
        {
          "name": "ADA",
          "percentage": 36,
          "color": "#0033ad"
        }
      ],
      "currentInvested": 4.87,
      "timeRemaining": 1686,
      "generatedAt": "2025-08-16T13:02:05.930032Z"
    },
    {
      "id": 6313,
      "name": "ETH/DOGE Bundle",
      "profit": "+11.7%",
      "duration": "21h",
      "risk": "Low",
      "assets": [
        {
          "name": "ETH",
          "percentage": 47,
          "color": "#627eea"
        },
        {
          "name": "DOGE",
          "percentage": 26,
          "color": "#d07c16"
        },
        {
          "name": "BTC",
          "percentage": 27,
          "color": "#f7931a"
        }
      ],
      "currentInvested": 10.12,
      "timeRemaining": 629,
      "generatedAt": "2025-08-16T13:02:05.930050Z"
    },
    {
      "id": 1067,
      "name": "SOL/DOGE Bundle",
      "profit": "+25.4%",
      "duration": "18h",
      "risk": "Low",
      "assets": [
        {
          "name": "SOL",
          "percentage": 44,
          "color": "#00d395"
        },
        {
          "name": "DOGE",
          "percentage": 26,
          "color": "#d07c16"
        },
        {
          "name": "XRP",
          "percentage": 30,
          "color": "#23292f"
        }
      ],
      "currentInvested": 1.24,
      "timeRemaining": 1680,
      "generatedAt": "2025-08-16T13:02:05.930068Z"
    }
  ]
}