{
  "lastUpdated": "2026-01-04T14:58:10.445518Z",
  "bundles": [
    {
      "id": 3787,
      "name": "DOT/ADA Bundle",
      "profit": "+12.9%",
      "duration": "1h",
      "risk": "Medium",
      "assets": [
        {
          "name": "DOT",
          "percentage": 27,
          "color": "#5d78ff"
        },
        {
          "name": "ADA",
          "percentage": 29,
          "color": "#0033ad"
        },
        {
          "name": "USDT",
          "percentage": 44,
          "color": "#26a17b"
        }
      ],
      "currentInvested": 1.6,
      "timeRemaining": 762,
      "generatedAt": "2026-01-04T14:58:10.445418Z"
    },
    {
      "id": 9222,
      "name": "BTC/DOT Bundle",
      "profit": "+10.4%",
      "duration": "18h",
      "risk": "High",
      "assets": [
        {
          "name": "BTC",
          "percentage": 27,
          "color": "#f7931a"
        },
        {
          "name": "DOT",
          "percentage": 47,
          "color": "#5d78ff"
        },
        {
          "name": "USDT",
          "percentage": 26,
          "color": "#26a17b"
        }
      ],
      "currentInvested": 2.85,
      "timeRemaining": 1490,
      "generatedAt": "2026-01-04T14:58:10.445442Z"
    },
    {
      "id": 4903,
      "name": "ETH/BTC Bundle",
      "profit": "+13.6%",
      "duration": "13h",
      "risk": "Low",
      "assets": [
        {
          "name": "ETH",
          "percentage": 25,
          "color": "#627eea"
        },
        {
          "name": "BTC",
          "percentage": 32,
          "color": "#f7931a"
        },
        {
          "name": "USDT",
          "percentage": 43,
          "color": "#26a17b"
        }
      ],
      "currentInvested": 1.79,
      "timeRemaining": 197,
      "generatedAt": "2026-01-04T14:58:10.445458Z"
    },
    {
      "id": 4108,
      "name": "ETH/BTC Bundle",
      "profit": "+20.4%",
      "duration": "7h",
      "risk": "Low",
      "assets": [
        {
          "name": "ETH",
          "percentage": 43,
          "color": "#627eea"
        },
        {
          "name": "BTC",
          "percentage": 41,
          "color": "#f7931a"
        },
        {
          "name": "ADA",
          "percentage": 16,
          "color": "#0033ad"
        }
      ],
      "currentInvested": 10.5,
      "timeRemaining": 1481,
      "generatedAt": "2026-01-04T14:58:10.445474Z"
    },
    {
      "id": 2692,
      "name": "SHIB/DOT Bundle",
      "profit": "+24.1%",
      "duration": "19h",
      "risk": "High",
      "assets": [
        {
          "name": "SHIB",
          "percentage": 31,
          "color": "#ffc000"
        },
        {
          "name": "DOT",
          "percentage": 24,
          "color": "#5d78ff"
        },
        {
          "name": "ADA",
          "percentage": 45,
          "color": "#0033ad"
        }
      ],
      "currentInvested": 3.17,
      "timeRemaining": 620,
      "generatedAt": "2026-01-04T14:58:10.445500Z"
    },
    {
      "id": 1967,
      "name": "XRP/DOGE Bundle",
      "profit": "+8.4%",
      "duration": "21h",
      "risk": "Low",
      "assets": [
        {
          "name": "XRP",
          "percentage": 25,
          "color": "#23292f"
        },
        {
          "name": "DOGE",
          "percentage": 43,
          "color": "#d07c16"
        },
        {
          "name": "DOT",
          "percentage": 32,
          "color": "#5d78ff"
        }
      ],
      "currentInvested": 2.02,
      "timeRemaining": 227,
      "generatedAt": "2026-01-04T14:58:10.445516Z"
    }
  ]
}