{
  "lastUpdated": "2025-09-08T07:54:14.133400Z",
  "bundles": [
    {
      "id": 9485,
      "name": "DOGE/ADA Bundle",
      "profit": "+13.4%",
      "duration": "21h",
      "risk": "Low",
      "assets": [
        {
          "name": "DOGE",
          "percentage": 22,
          "color": "#d07c16"
        },
        {
          "name": "ADA",
          "percentage": 32,
          "color": "#0033ad"
        },
        {
          "name": "BNB",
          "percentage": 46,
          "color": "#f3ba2f"
        }
      ],
      "currentInvested": 11.6,
      "timeRemaining": 85,
      "generatedAt": "2025-09-08T07:54:14.133299Z"
    },
    {
      "id": 6402,
      "name": "DOT/SOL Bundle",
      "profit": "+15.9%",
      "duration": "22h",
      "risk": "Medium",
      "assets": [
        {
          "name": "DOT",
          "percentage": 44,
          "color": "#5d78ff"
        },
        {
          "name": "SOL",
          "percentage": 38,
          "color": "#00d395"
        },
        {
          "name": "DOGE",
          "percentage": 18,
          "color": "#d07c16"
        }
      ],
      "currentInvested": 4.05,
      "timeRemaining": 773,
      "generatedAt": "2025-09-08T07:54:14.133327Z"
    },
    {
      "id": 4625,
      "name": "USDT/BNB Bundle",
      "profit": "+19.5%",
      "duration": "9h",
      "risk": "Low",
      "assets": [
        {
          "name": "USDT",
          "percentage": 26,
          "color": "#26a17b"
        },
        {
          "name": "BNB",
          "percentage": 37,
          "color": "#f3ba2f"
        },
        {
          "name": "ADA",
          "percentage": 37,
          "color": "#0033ad"
        }
      ],
      "currentInvested": 0.93,
      "timeRemaining": 307,
      "generatedAt": "2025-09-08T07:54:14.133346Z"
    },
    {
      "id": 4295,
      "name": "BNB/SHIB Bundle",
      "profit": "+20.4%",
      "duration": "22h",
      "risk": "Low",
      "assets": [
        {
          "name": "BNB",
          "percentage": 18,
          "color": "#f3ba2f"
        },
        {
          "name": "SHIB",
          "percentage": 51,
          "color": "#ffc000"
        },
        {
          "name": "BTC",
          "percentage": 31,
          "color": "#f7931a"
        }
      ],
      "currentInvested": 9.35,
      "timeRemaining": 807,
      "generatedAt": "2025-09-08T07:54:14.133364Z"
    },
    {
      "id": 1177,
      "name": "DOT/SHIB Bundle",
      "profit": "+13.3%",
      "duration": "18h",
      "risk": "High",
      "assets": [
        {
          "name": "DOT",
          "percentage": 35,
          "color": "#5d78ff"
        },
        {
          "name": "SHIB",
          "percentage": 34,
          "color": "#ffc000"
        },
        {
          "name": "ADA",
          "percentage": 31,
          "color": "#0033ad"
        }
      ],
      "currentInvested": 12.07,
      "timeRemaining": 240,
      "generatedAt": "2025-09-08T07:54:14.133382Z"
    },
    {
      "id": 9069,
      "name": "DOT/DOGE Bundle",
      "profit": "+9.8%",
      "duration": "5h",
      "risk": "Medium",
      "assets": [
        {
          "name": "DOT",
          "percentage": 34,
          "color": "#5d78ff"
        },
        {
          "name": "DOGE",
          "percentage": 36,
          "color": "#d07c16"
        },
        {
          "name": "ETH",
          "percentage": 30,
          "color": "#627eea"
        }
      ],
      "currentInvested": 0.31,
      "timeRemaining": 967,
      "generatedAt": "2025-09-08T07:54:14.133398Z"
    }
  ]
}