{
  "lastUpdated": "2025-09-04T03:53:14.105774Z",
  "bundles": [
    {
      "id": 4154,
      "name": "BNB/XRP Bundle",
      "profit": "+8.0%",
      "duration": "11h",
      "risk": "High",
      "assets": [
        {
          "name": "BNB",
          "percentage": 25,
          "color": "#f3ba2f"
        },
        {
          "name": "XRP",
          "percentage": 44,
          "color": "#23292f"
        },
        {
          "name": "DOT",
          "percentage": 31,
          "color": "#5d78ff"
        }
      ],
      "currentInvested": 6.15,
      "timeRemaining": 863,
      "generatedAt": "2025-09-04T03:53:14.105670Z"
    },
    {
      "id": 2842,
      "name": "BNB/SHIB Bundle",
      "profit": "+23.8%",
      "duration": "1h",
      "risk": "Low",
      "assets": [
        {
          "name": "BNB",
          "percentage": 39,
          "color": "#f3ba2f"
        },
        {
          "name": "SHIB",
          "percentage": 22,
          "color": "#ffc000"
        },
        {
          "name": "BTC",
          "percentage": 39,
          "color": "#f7931a"
        }
      ],
      "currentInvested": 13.97,
      "timeRemaining": 754,
      "generatedAt": "2025-09-04T03:53:14.105698Z"
    },
    {
      "id": 6288,
      "name": "DOGE/XRP Bundle",
      "profit": "+17.8%",
      "duration": "21h",
      "risk": "Medium",
      "assets": [
        {
          "name": "DOGE",
          "percentage": 47,
          "color": "#d07c16"
        },
        {
          "name": "XRP",
          "percentage": 19,
          "color": "#23292f"
        },
        {
          "name": "SHIB",
          "percentage": 34,
          "color": "#ffc000"
        }
      ],
      "currentInvested": 0.4,
      "timeRemaining": 322,
      "generatedAt": "2025-09-04T03:53:14.105719Z"
    },
    {
      "id": 3142,
      "name": "XRP/BNB Bundle",
      "profit": "+11.3%",
      "duration": "23h",
      "risk": "High",
      "assets": [
        {
          "name": "XRP",
          "percentage": 38,
          "color": "#23292f"
        },
        {
          "name": "BNB",
          "percentage": 16,
          "color": "#f3ba2f"
        },
        {
          "name": "USDT",
          "percentage": 46,
          "color": "#26a17b"
        }
      ],
      "currentInvested": 1.33,
      "timeRemaining": 311,
      "generatedAt": "2025-09-04T03:53:14.105737Z"
    },
    {
      "id": 9634,
      "name": "DOGE/BNB Bundle",
      "profit": "+21.6%",
      "duration": "3h",
      "risk": "Medium",
      "assets": [
        {
          "name": "DOGE",
          "percentage": 60,
          "color": "#d07c16"
        },
        {
          "name": "BNB",
          "percentage": 19,
          "color": "#f3ba2f"
        },
        {
          "name": "ETH",
          "percentage": 21,
          "color": "#627eea"
        }
      ],
      "currentInvested": 11.11,
      "timeRemaining": 966,
      "generatedAt": "2025-09-04T03:53:14.105755Z"
    },
    {
      "id": 1818,
      "name": "XRP/DOGE Bundle",
      "profit": "+6.5%",
      "duration": "4h",
      "risk": "Medium",
      "assets": [
        {
          "name": "XRP",
          "percentage": 41,
          "color": "#23292f"
        },
        {
          "name": "DOGE",
          "percentage": 26,
          "color": "#d07c16"
        },
        {
          "name": "BTC",
          "percentage": 33,
          "color": "#f7931a"
        }
      ],
      "currentInvested": 8.72,
      "timeRemaining": 1503,
      "generatedAt": "2025-09-04T03:53:14.105772Z"
    }
  ]
}