{
  "lastUpdated": "2025-12-19T19:39:24.217972Z",
  "bundles": [
    {
      "id": 5563,
      "name": "SOL/ADA Bundle",
      "profit": "+17.3%",
      "duration": "12h",
      "risk": "Low",
      "assets": [
        {
          "name": "SOL",
          "percentage": 38,
          "color": "#00d395"
        },
        {
          "name": "ADA",
          "percentage": 44,
          "color": "#0033ad"
        },
        {
          "name": "BNB",
          "percentage": 18,
          "color": "#f3ba2f"
        }
      ],
      "currentInvested": 12.21,
      "timeRemaining": 412,
      "generatedAt": "2025-12-19T19:39:24.217869Z"
    },
    {
      "id": 8054,
      "name": "DOT/BTC Bundle",
      "profit": "+16.1%",
      "duration": "8h",
      "risk": "High",
      "assets": [
        {
          "name": "DOT",
          "percentage": 26,
          "color": "#5d78ff"
        },
        {
          "name": "BTC",
          "percentage": 23,
          "color": "#f7931a"
        },
        {
          "name": "BNB",
          "percentage": 51,
          "color": "#f3ba2f"
        }
      ],
      "currentInvested": 1.51,
      "timeRemaining": 1487,
      "generatedAt": "2025-12-19T19:39:24.217895Z"
    },
    {
      "id": 5147,
      "name": "ADA/BNB Bundle",
      "profit": "+17.2%",
      "duration": "17h",
      "risk": "Medium",
      "assets": [
        {
          "name": "ADA",
          "percentage": 38,
          "color": "#0033ad"
        },
        {
          "name": "BNB",
          "percentage": 39,
          "color": "#f3ba2f"
        },
        {
          "name": "DOGE",
          "percentage": 23,
          "color": "#d07c16"
        }
      ],
      "currentInvested": 11.67,
      "timeRemaining": 449,
      "generatedAt": "2025-12-19T19:39:24.217914Z"
    },
    {
      "id": 6751,
      "name": "ADA/XRP Bundle",
      "profit": "+8.4%",
      "duration": "11h",
      "risk": "Low",
      "assets": [
        {
          "name": "ADA",
          "percentage": 22,
          "color": "#0033ad"
        },
        {
          "name": "XRP",
          "percentage": 40,
          "color": "#23292f"
        },
        {
          "name": "SOL",
          "percentage": 38,
          "color": "#00d395"
        }
      ],
      "currentInvested": 0.3,
      "timeRemaining": 69,
      "generatedAt": "2025-12-19T19:39:24.217934Z"
    },
    {
      "id": 9251,
      "name": "SHIB/DOT Bundle",
      "profit": "+20.4%",
      "duration": "1h",
      "risk": "Medium",
      "assets": [
        {
          "name": "SHIB",
          "percentage": 40,
          "color": "#ffc000"
        },
        {
          "name": "DOT",
          "percentage": 18,
          "color": "#5d78ff"
        },
        {
          "name": "SOL",
          "percentage": 42,
          "color": "#00d395"
        }
      ],
      "currentInvested": 7.82,
      "timeRemaining": 1124,
      "generatedAt": "2025-12-19T19:39:24.217953Z"
    },
    {
      "id": 7339,
      "name": "XRP/ETH Bundle",
      "profit": "+5.4%",
      "duration": "14h",
      "risk": "Medium",
      "assets": [
        {
          "name": "XRP",
          "percentage": 24,
          "color": "#23292f"
        },
        {
          "name": "ETH",
          "percentage": 57,
          "color": "#627eea"
        },
        {
          "name": "USDT",
          "percentage": 19,
          "color": "#26a17b"
        }
      ],
      "currentInvested": 0.42,
      "timeRemaining": 1196,
      "generatedAt": "2025-12-19T19:39:24.217970Z"
    }
  ]
}